xgid2anki/.gitignore
xgid2anki/__init__.py
xgid2anki/analyze_positions.py
xgid2anki/build_deck.py
xgid2anki/cli.py
xgid2anki/download_bglog.py
xgid2anki/ensure_headless_chromium.py
xgid2anki/gnubg_pos_analysis.py
xgid2anki/id_scheme.py
xgid2anki/parse_gnubg_eval.py
xgid2anki/pipeline.py
xgid2anki/validate_xgid.py
xgid2anki/xgid2svg.py
xgid2anki/templates/cube_back.html
xgid2anki/templates/cube_front.html
xgid2anki/templates/move_back.html
xgid2anki/templates/move_front.html
xgid2anki/templates/shared_styles.bkup.css
xgid2anki/templates/shared_styles.css
xgid2anki/templates/takepass_back.html
xgid2anki/templates/takepass_front.html
xgid2anki/themes/default_theme.json
xgid2anki-0.1.4.dist-info/METADATA
xgid2anki-0.1.4.dist-info/WHEEL
xgid2anki-0.1.4.dist-info/entry_points.txt
xgid2anki-0.1.4.dist-info/licenses/LICENSE
xgid2anki-0.1.4.dist-info/RECORD
