Metadata-Version: 2.4
Name: xgid2anki
Version: 0.1.4
Summary: Convert a list of backgammon XGIDs into an interactive Anki study deck.
Project-URL: Homepage, https://github.com/ngvlamis/xgid2anki
Project-URL: Repository, https://github.com/ngvlamis/xgid2anki
Project-URL: Issues, https://github.com/ngvlamis/xgid2anki/issues
Author-email: "Nicholas G. Vlamis" <nvlamis@gc.cuny.edu>
License: GPL-3.0-or-later
License-File: LICENSE
Keywords: anki,backgammon,bglog,deck,gnubg,study,svg,xgid
Classifier: Development Status :: 4 - Beta
Classifier: Environment :: Console
Classifier: Intended Audience :: End Users/Desktop
Classifier: License :: OSI Approved :: GNU General Public License v3 or later (GPLv3+)
Classifier: Operating System :: OS Independent
Classifier: Programming Language :: Python :: 3
Classifier: Programming Language :: Python :: 3.10
Classifier: Programming Language :: Python :: 3.11
Classifier: Programming Language :: Python :: 3.12
Classifier: Topic :: Games/Entertainment :: Board Games
Requires-Python: >=3.10
Requires-Dist: genanki
Requires-Dist: platformdirs
Requires-Dist: playwright>=1.55.0
Requires-Dist: pyyaml
Requires-Dist: tqdm
